apibara/__init__.py
apibara/cursor.py
apibara/indexer/__init__.py
apibara/indexer/configuration.py
apibara/indexer/indexer.py
apibara/indexer/info.py
apibara/indexer/runner.py
apibara/indexer/storage.py
apibara/protocol/__init__.py
apibara/protocol/client.py
apibara/protocol/proto/__init__.py
apibara/protocol/proto/stream_pb2.py
apibara/protocol/proto/stream_pb2.pyi
apibara/protocol/proto/stream_pb2_grpc.py
apibara/protocol/proto/stream_pb2_grpc.pyi
apibara/starknet/__init__.py
apibara/starknet/cursor.py
apibara/starknet/felt.py
apibara/starknet/filter.py
apibara/starknet/indexer.py
apibara/starknet/proto/__init__.py
apibara/starknet/proto/filter_pb2.py
apibara/starknet/proto/filter_pb2.pyi
apibara/starknet/proto/filter_pb2_grpc.py
apibara/starknet/proto/filter_pb2_grpc.pyi
apibara/starknet/proto/starknet_pb2.py
apibara/starknet/proto/starknet_pb2.pyi
apibara/starknet/proto/starknet_pb2_grpc.py
apibara/starknet/proto/starknet_pb2_grpc.pyi
apibara/starknet/proto/types_pb2.py
apibara/starknet/proto/types_pb2.pyi
apibara/starknet/proto/types_pb2_grpc.py
apibara/starknet/proto/types_pb2_grpc.pyi
apibara-0.8.0.dist-info/LICENSE.txt
apibara-0.8.0.dist-info/METADATA
apibara-0.8.0.dist-info/WHEEL
apibara-0.8.0.dist-info/RECORD
