Metadata-Version: 2.1
Name: apibara
Version: 0.8.0
Summary: Apibara cliend SDK. Stream and transform on-chain data with Python.
Home-page: https://www.apibara.com
License: Apache-2.0
Keywords: ethereum,web3,starknet
Author: Francesco Ceccon
Author-email: francesco@apibara.com
Requires-Python: >=3.8,<3.13
Classifier: Development Status :: 3 - Alpha
Classifier: Intended Audience :: Developers
Classifier: License :: OSI Approved :: Apache Software License
Classifier: Programming Language :: Python :: 3
Classifier: Programming Language :: Python :: 3.8
Classifier: Programming Language :: Python :: 3.9
Classifier: Programming Language :: Python :: 3.10
Classifier: Programming Language :: Python :: 3.11
Classifier: Programming Language :: Python :: 3.12
Provides-Extra: indexer
Requires-Dist: grpcio (>=1.50,<2.0)
Requires-Dist: protobuf (>=4.20,<5)
Requires-Dist: pymongo (>=4.3.3,<5.0.0) ; extra == "indexer"
Project-URL: Repository, https://github.com/apibara/python-sdk
